{
    "mp_biodome": "Aquarium",
    "mp_spire": "Breach",
    "mp_sector": "Combine",
    "mp_apartments": "Evac",
    "mp_chinatown": "Exodus",
    "mp_veiled": "Fringe",
    "mp_havoc": "Havoc",
    "mp_ethiopia": "Hunted",
    "mp_infection": "Infection",
    "mp_metro": "Metro",
    "mp_redwood": "Redwood",
    "mp_stronghold": "Stronghold",
    "mp_nuketown_x": "Nuk3town",
    "mp_shrine": "Berserk",
    "mp_ruins": "Citadel",
    "mp_cryogen": "Cryogen",
    "mp_rome": "Empire",
    "mp_crucible": "Gauntlet",
    "mp_kung_fu": "Knockout",
    "mp_miniature": "Micro",
    "mp_western": "Outlaw",
    "mp_conduit": "Rift",
    "mp_rise": "Rise",
    "mp_arena": "Rumble",
    "mp_city": "Rupture",
    "mp_airship": "Skyjacked",
    "mp_aerospace": "Spire",
    "mp_waterpark": "Splash",
    "mp_banzai": "Verge",
    "mp_veiled_heyday": "Fringe Night",
    "mp_redwood_ice": "Redwood Snow",

    "cp_sh_mobile": "Mobile",
    "cp_sh_singapore": "Singapore",
    "cp_sh_cairo": "Cairo",
    "cp_mi_eth_prologue": "Black Ops",
    "cp_mi_zurich_newworld": "New World",
    "cp_mi_sing_blackstation": "In Darkness",
    "cp_mi_sing_biodomes": "Provocation",
    "cp_mi_sing_sgen": "Hypocenter",
    "cp_mi_sing_vengeance": "Vengeance",
    "cp_mi_cairo_ramses": "Rise & Fall",
    "cp_mi_cairo_infection": "Demon Within",
    "cp_mi_cairo_aquifer": "Sand Castle",
    "cp_mi_cairo_lotus": "Lotus Towers",
    "cp_mi_zurich_coalescence": "Life",

    "zm_zod": "Shadows of Evil",
    "zm_castle": "Der Eisendrache",
    "zm_island": "Zetsubou No Shima",
    "zm_stalingrad": "Gorod Krovi",
    "zm_genesis": "Revelations",
    "zm_cosmodrome": "Ascension",
    "zm_theater": "Kino der Toten",
    "zm_moon": "Moon",
    "zm_prototype": "Nacht der Untoten",
    "zm_tomb": "Origins",
    "zm_temple": "Shangri-La",
    "zm_sumpf": "Shi No Numa",
    "zm_factory": "The Giant",
    "zm_asylum": "Verrückt"
}